openethos_securityguard-1.2.6.dist-info/licenses/LICENSE
securityguard/__init__.py
securityguard/__main__.py
securityguard/enums/__init__.py
securityguard/main/__init__.py
securityguard/main/config.py
securityguard/main/workflow.py
openethos_securityguard-1.2.6.dist-info/METADATA
openethos_securityguard-1.2.6.dist-info/WHEEL
openethos_securityguard-1.2.6.dist-info/entry_points.txt
openethos_securityguard-1.2.6.dist-info/top_level.txt
openethos_securityguard-1.2.6.dist-info/RECORD
